info_nce/__init__.py
info_nce_pytorch-0.1.4.dist-info/LICENSE
info_nce_pytorch-0.1.4.dist-info/METADATA
info_nce_pytorch-0.1.4.dist-info/WHEEL
info_nce_pytorch-0.1.4.dist-info/top_level.txt
info_nce_pytorch-0.1.4.dist-info/RECORD
