Metadata-Version: 2.1
Name: info-nce-pytorch
Version: 0.1.4
Summary: PyTorch implementation of the InfoNCE loss for self-supervised learning.
Home-page: https://github.com/RElbers/info-nce-pytorch
Author: Robin Elbers
License: MIT
Platform: UNKNOWN
License-File: LICENSE
Requires-Dist: torch
